py_horned_owl_certus-0.5.2.dist-info/METADATA
py_horned_owl_certus-0.5.2.dist-info/WHEEL
py_horned_owl_certus-0.5.2.dist-info/licenses/COPYING
py_horned_owl_certus-0.5.2.dist-info/licenses/COPYING.lesser
pyhornedowl/model/__init__.py
pyhornedowl/model/__init__.pyi
pyhornedowl/py.typed
pyhornedowl/__init__.py
pyhornedowl/__init__.pyi
pyhornedowl/pyhornedowl.pyd
py_horned_owl_certus-0.5.2.dist-info/RECORD
