Metadata-Version: 2.4
Name: py-horned-owl-certus
Version: 0.5.2
Classifier: Programming Language :: Rust
Classifier: Programming Language :: Python :: Implementation :: CPython
Classifier: Programming Language :: Python :: Implementation :: PyPy
License-File: COPYING
License-File: COPYING.lesser
Author: Certus Group <engineering@certusgroup.com>
Author-email: Certus Group <engineering@certusgroup.com>
License: LGPL-3.0-or-later
Requires-Python: >=3.7
